{"eventTradingState":{"header":{"latencyTiming":{"activityTimes":[{"activity":"messageReceivedFromLsports","epoch":1594056023070},{"activity":"messageSentFromProxy","epoch":1594056023074},{"activity":"messageReceivedFromProxy","epoch":1594056023078},{"activity":"messageHandleInExecutor","epoch":1594056023078},{"activity":"sendingToBetsync","epoch":1594056023078}],"eventId":5625107,"originatingReqId":"f29a77da-f808-48e8-90aa-99183613e3b9","originatingProvider":"LSPORTS"}},"prices":{"market":[]},"gatedMarkets":[],"suspendedInChannels":[],"undisplayedInChannels":[],"gatedInChannels":[],"settings":[],"pitchers":[],"state":"ACTIVE","offeredInplay":true,"inplay":true,"displayed":true,"extId":"5625107"},"credential":{"username":"lsportsbetsyncuser","password":"dkd9hdg6283hbfdshdasidy23123"},"systemcode":"LSPORTS","partitioned":false}