{"eventTradingState":{"header":{"latencyTiming":{"activityTimes":[{"activity":"messageReceivedFromLsports","epoch":1594053823502},{"activity":"messageSentFromProxy","epoch":1594053823503},{"activity":"messageReceivedFromProxy","epoch":1594053823509},{"activity":"messageHandleInExecutor","epoch":1594053823515},{"activity":"sendingToBetsync","epoch":1594053823515}],"eventId":5625107,"originatingReqId":"6a3d4b26-68cf-4a06-bc2f-085877d41a0e","originatingProvider":"LSPORTS"}},"prices":{"market":[]},"gatedMarkets":[],"suspendedInChannels":[],"undisplayedInChannels":[],"gatedInChannels":[],"settings":[],"pitchers":[],"state":"ACTIVE","offeredInplay":true,"inplay":true,"displayed":true,"extId":"5625107"},"credential":{"username":"lsportsbetsyncuser","password":"dkd9hdg6283hbfdshdasidy23123"},"systemcode":"LSPORTS","partitioned":false}