{"eventTradingState":{"header":{"latencyTiming":{"activityTimes":[{"activity":"messageReceivedFromLsports","epoch":1593939994574},{"activity":"messageSentFromProxy","epoch":1593939994580},{"activity":"messageReceivedFromProxy","epoch":1593939994583},{"activity":"messageHandleInExecutor","epoch":1593939994583},{"activity":"sendingToBetsync","epoch":1593939994583}],"eventId":5621497,"originatingReqId":"6784ebe5-b618-44c5-a022-a6a273921eb8","originatingProvider":"LSPORTS"}},"prices":{"market":[{"channel":[{"selection":[{"type":"BH","state":"SUSPENDED","displayed":false},{"type":"AH","state":"SUSPENDED","displayed":false}],"channel":"INTERNET"}],"state":"SUSPENDED","displayed":false,"type":"TENNIS:P:RX","subtype":"S1#2.0"}]},"gatedMarkets":[],"suspendedInChannels":[],"undisplayedInChannels":[],"gatedInChannels":[],"settings":[],"pitchers":[],"state":"ACTIVE","offeredInplay":true,"inplay":true,"displayed":true,"extId":"5621497"},"credential":{"username":"lsportsbetsyncuser","password":"dkd9hdg6283hbfdshdasidy23123"},"systemcode":"LSPORTS","partitioned":false}