{"eventTradingState":{"header":{"latencyTiming":{"activityTimes":[{"activity":"messageReceivedFromLsports","epoch":1593942619216},{"activity":"messageSentFromProxy","epoch":1593942619217},{"activity":"messageReceivedFromProxy","epoch":1593942619223},{"activity":"messageHandleInExecutor","epoch":1593942619231},{"activity":"sendingToBetsync","epoch":1593942619231}],"eventId":5621497,"originatingReqId":"8bd85b08-d861-4e5d-8d76-5386a12a78d7","originatingProvider":"LSPORTS"}},"prices":{"market":[{"channel":[{"selection":[{"type":"0-2","state":"ACTIVE","displayed":true,"decimalOdds":1.062},{"type":"2-1","state":"ACTIVE","displayed":true,"decimalOdds":15.0}],"channel":"INTERNET"}],"state":"OPEN","displayed":true,"type":"TENNIS:FT:CS"}]},"gatedMarkets":[],"suspendedInChannels":[],"undisplayedInChannels":[],"gatedInChannels":[],"settings":[],"pitchers":[],"state":"ACTIVE","offeredInplay":true,"inplay":true,"displayed":true,"extId":"5621497"},"credential":{"username":"lsportsbetsyncuser","password":"dkd9hdg6283hbfdshdasidy23123"},"systemcode":"LSPORTS","partitioned":false}