{"eventTradingState":{"header":{"latencyTiming":{"activityTimes":[{"activity":"messageReceivedFromLsports","epoch":1593974217503},{"activity":"messageSentFromProxy","epoch":1593974217505},{"activity":"messageReceivedFromProxy","epoch":1593974217509},{"activity":"messageHandleInExecutor","epoch":1593974217509},{"activity":"sendingToBetsync","epoch":1593974217513}],"eventId":5591553,"originatingReqId":"b77e6262-517a-4c66-bc1d-bac10ae90af6","originatingProvider":"LSPORTS"}},"prices":{"market":[]},"gatedMarkets":[],"results":{"market":[]},"suspendedInChannels":[],"undisplayedInChannels":[],"gatedInChannels":[],"settings":[],"pitchers":[],"state":"ACTIVE","offeredInplay":true,"inplay":true,"displayed":true,"extId":"5591553"},"credential":{"username":"lsportsbetsyncuser","password":"dkd9hdg6283hbfdshdasidy23123"},"systemcode":"LSPORTS","partitioned":false}