{"eventTradingState":{"header":{"latencyTiming":{"activityTimes":[{"activity":"messageReceivedFromLsports","epoch":1593973892403},{"activity":"messageSentFromProxy","epoch":1593973892408},{"activity":"messageReceivedFromProxy","epoch":1593973892410},{"activity":"messageHandleInExecutor","epoch":1593973892448},{"activity":"sendingToBetsync","epoch":1593973892448}],"eventId":5591553,"originatingReqId":"32df9b65-9899-475c-83c7-d90789d3861d","originatingProvider":"LSPORTS"}},"prices":{"market":[]},"gatedMarkets":[],"suspendedInChannels":[],"undisplayedInChannels":[],"gatedInChannels":[],"settings":[],"pitchers":[],"state":"ACTIVE","offeredInplay":true,"inplay":true,"displayed":true,"extId":"5591553"},"credential":{"username":"lsportsbetsyncuser","password":"dkd9hdg6283hbfdshdasidy23123"},"systemcode":"LSPORTS","partitioned":false}