{"eventTradingState":{"header":{"latencyTiming":{"activityTimes":[{"activity":"messageReceivedFromLsports","epoch":1593976761739},{"activity":"messageSentFromProxy","epoch":1593976761740},{"activity":"messageReceivedFromProxy","epoch":1593976761742},{"activity":"messageHandleInExecutor","epoch":1593976761742},{"activity":"sendingToBetsync","epoch":1593976761743}],"eventId":5591553,"originatingReqId":"e26117ec-60f8-4c56-bdc5-aaa4b7aa670f","originatingProvider":"LSPORTS"}},"prices":{"market":[]},"gatedMarkets":[],"suspendedInChannels":[],"undisplayedInChannels":[],"gatedInChannels":[],"settings":[],"pitchers":[],"state":"ACTIVE","offeredInplay":true,"inplay":true,"displayed":true,"extId":"5591553"},"credential":{"username":"lsportsbetsyncuser","password":"dkd9hdg6283hbfdshdasidy23123"},"systemcode":"LSPORTS","partitioned":false}