{"eventTradingState":{"header":{"latencyTiming":{"activityTimes":[{"activity":"messageReceivedFromLsports","epoch":1593973157738},{"activity":"messageSentFromProxy","epoch":1593973157749},{"activity":"messageReceivedFromProxy","epoch":1593973157750},{"activity":"messageHandleInExecutor","epoch":1593973157778},{"activity":"sendingToBetsync","epoch":1593973157779}],"eventId":5591553,"originatingReqId":"4090f201-89bf-4acd-80fd-e86588c9ae75","originatingProvider":"LSPORTS"}},"prices":{"market":[]},"gatedMarkets":[],"suspendedInChannels":[],"undisplayedInChannels":[],"gatedInChannels":[],"settings":[],"pitchers":[],"state":"ACTIVE","offeredInplay":true,"inplay":true,"displayed":true,"extId":"5591553"},"credential":{"username":"lsportsbetsyncuser","password":"dkd9hdg6283hbfdshdasidy23123"},"systemcode":"LSPORTS","partitioned":false}