{"eventTradingState":{"header":{"latencyTiming":{"activityTimes":[{"activity":"messageReceivedFromLsports","epoch":1593897941054},{"activity":"messageSentFromProxy","epoch":1593897941055},{"activity":"messageReceivedFromProxy","epoch":1593897941092},{"activity":"messageHandleInExecutor","epoch":1593897941092},{"activity":"sendingToBetsync","epoch":1593897941092}],"eventId":5614761,"originatingReqId":"7e8148c4-30f9-459c-9e0c-e6fc0216c9ec","originatingProvider":"LSPORTS"}},"prices":{"market":[{"channel":[{"selection":[{"type":"Under","state":"ACTIVE","displayed":true,"decimalOdds":1.833},{"type":"Over","state":"ACTIVE","displayed":true,"decimalOdds":1.833}],"channel":"INTERNET"}],"state":"OPEN","displayed":true,"type":"BASKETBALL:FTOT:OU","subtype":"M#127.5"},{"channel":[{"selection":[{"type":"Under","state":"SUSPENDED","displayed":false},{"type":"Over","state":"SUSPENDED","displayed":false}],"channel":"INTERNET"}],"state":"SUSPENDED","displayed":false,"type":"BASKETBALL:FTOT:OU","subtype":"M#128.5"}]},"gatedMarkets":[],"suspendedInChannels":[],"undisplayedInChannels":[],"gatedInChannels":[],"settings":[],"pitchers":[],"state":"ACTIVE","offeredInplay":true,"inplay":true,"displayed":true,"extId":"5614761"},"credential":{"username":"lsportsbetsyncuser","password":"dkd9hdg6283hbfdshdasidy23123"},"systemcode":"LSPORTS","partitioned":false}