{"eventTradingState":{"header":{"latencyTiming":{"activityTimes":[{"activity":"messageReceivedFromLsports","epoch":1593970089361},{"activity":"messageSentFromProxy","epoch":1593970089374},{"activity":"messageReceivedFromProxy","epoch":1593970089376},{"activity":"messageHandleInExecutor","epoch":1593970089399},{"activity":"sendingToBetsync","epoch":1593970089400}],"eventId":5587530,"originatingReqId":"223324a3-6445-4ce8-8c87-a25aedffa0d3","originatingProvider":"LSPORTS"}},"prices":{"market":[]},"gatedMarkets":[],"suspendedInChannels":[],"undisplayedInChannels":[],"gatedInChannels":[],"settings":[],"pitchers":[],"state":"ACTIVE","offeredInplay":true,"inplay":true,"displayed":true,"extId":"5587530"},"credential":{"username":"lsportsbetsyncuser","password":"dkd9hdg6283hbfdshdasidy23123"},"systemcode":"LSPORTS","partitioned":false}