{"ElapsedTimeMatchIncident":{"subClass":"ElapsedTimeMatchIncident","undo":false,"elapsedTimeSecs":960,"eventId":0,"incidentId":"2afe0be1-c699-4ac3-8d92-7669cbdd8249","sourceSystem":"LSPORTS","externalEventId":"5604129","incidentFeedTimeStamp":0,"matchStateFromFeed":{"subClass":"FootballMatchStateFromFeed","goalsA":0,"goalsB":0,"firstHalfGoalsA":0,"firstHalfGoalsB":0,"cornersA":2,"cornersB":0,"yellowCardA":0,"yellowCardB":0,"redCardA":0,"redCardB":0,"matchPeriod":["FootballMatchPeriod","IN_FIRST_HALF"]},"incidentSubType":"SET_MATCH_CLOCK","description":"incident SET_MATCH_CLOCK in 960 second , match state: FootballMatchStateFromFeed [goalsA=0, goalsB=0, firstHalfGoalsA=0, firstHalfGoalsB=0, yellowCardA=0, yellowCardB=0, redCardA=0, redCardB=0, cornersA=2, cornersB=0, matchPeriod=IN_FIRST_HALF]"}}