{"eventTradingState":{"header":{"latencyTiming":{"activityTimes":[{"activity":"messageReceivedFromLsports","epoch":1594218505736},{"activity":"messageSentFromProxy","epoch":1594218505753},{"activity":"messageReceivedFromProxy","epoch":1594218505755},{"activity":"messageHandleInExecutor","epoch":1594218505756},{"activity":"sendingToBetsync","epoch":1594218505756}],"eventId":5604129,"originatingReqId":"63dddc75-73e8-4668-a1ed-25d5d4cf91cf","originatingProvider":"LSPORTS"}},"prices":{"market":[{"channel":[{"selection":[{"type":"XB","state":"ACTIVE","displayed":true,"decimalOdds":1.3}],"channel":"INTERNET"}],"state":"OPEN","displayed":true,"type":"SOCCER:FT:DBLC"},{"channel":[{"selection":[{"type":"A","state":"ACTIVE","displayed":true,"decimalOdds":3.4}],"channel":"INTERNET"}],"state":"OPEN","displayed":true,"type":"SOCCER:FT:AXB","subtype":"M"}]},"gatedMarkets":[],"bookmakerPrices":{"bookies":[{"bookie":"Bet365","marketPrices":{"market":[{"channel":[{"selection":[{"type":"XB","state":"ACTIVE","priceType":"LIVE_PRICE","displayed":true,"decimalOdds":1.3}],"channel":"INTERNET"}],"state":"OPEN","type":"SOCCER:FT:DBLC","subtype":"M","line":""},{"channel":[{"selection":[{"type":"A","state":"ACTIVE","priceType":"LIVE_PRICE","displayed":true,"decimalOdds":3.4}],"channel":"INTERNET"}],"state":"OPEN","type":"SOCCER:FT:AXB","subtype":"M","line":""},{"channel":[{"selection":[{"type":"1-1","state":"ACTIVE","priceType":"LIVE_PRICE","displayed":true,"decimalOdds":13.0},{"type":"2-2","state":"SUSPENDED","priceType":"LIVE_PRICE","displayed":true}],"channel":"INTERNET"}],"state":"OPEN","type":"SOCCER:FT:CS","subtype":"M","line":""},{"channel":[{"selection":[{"type":"AH","state":"ACTIVE","name":"Biashara United +1","priceType":"LIVE_PRICE","displayed":true,"decimalOdds":1.167},{"type":"BH","state":"ACTIVE","name":"Ruvu Shooting -1","priceType":"LIVE_PRICE","displayed":true,"decimalOdds":19.0},{"type":"DH","state":"ACTIVE","name":"Draw -1","priceType":"LIVE_PRICE","displayed":true,"decimalOdds":5.0}],"channel":"INTERNET"}],"state":"OPEN","type":"SOCCER:FT:3HCP","subtype":"M#1","line":"1"},{"channel":[{"selection":[{"type":"AH","state":"ACTIVE","name":"Biashara United -1","priceType":"LIVE_PRICE","displayed":true,"decimalOdds":13.0},{"type":"BH","state":"ACTIVE","name":"Ruvu Shooting +1","priceType":"LIVE_PRICE","displayed":true,"decimalOdds":1.3},{"type":"DH","state":"ACTIVE","name":"Draw +1","priceType":"LIVE_PRICE","displayed":true,"decimalOdds":4.0}],"channel":"INTERNET"}],"state":"OPEN","type":"SOCCER:FT:3HCP","subtype":"M#-1","line":"-1"}]},"inplay":true,"eventId":5604129}],"eventId":5604129},"suspendedInChannels":[],"undisplayedInChannels":[],"gatedInChannels":[],"settings":[],"pitchers":[],"state":"ACTIVE","offeredInplay":true,"inplay":true,"displayed":true,"extId":"5604129"},"credential":{"username":"lsportsbetsyncuser","password":"dkd9hdg6283hbfdshdasidy23123"},"systemcode":"LSPORTS","partitioned":false}