{"eventTradingState":{"header":{"latencyTiming":{"activityTimes":[{"activity":"messageReceivedFromLsports","epoch":1594219544728},{"activity":"messageSentFromProxy","epoch":1594219544729},{"activity":"messageReceivedFromProxy","epoch":1594219544732},{"activity":"messageHandleInExecutor","epoch":1594219544732},{"activity":"sendingToBetsync","epoch":1594219544733}],"eventId":5604129,"originatingReqId":"f4926d89-6520-42b7-bc5d-fbbf4cd35e4e","originatingProvider":"LSPORTS"}},"prices":{"market":[{"channel":[{"selection":[{"type":"XB","state":"ACTIVE","displayed":true,"decimalOdds":1.083},{"type":"AB","state":"ACTIVE","displayed":true,"decimalOdds":4.333}],"channel":"INTERNET"}],"state":"OPEN","displayed":true,"type":"SOCCER:FT:DBLC"},{"channel":[{"selection":[{"type":"A","state":"ACTIVE","displayed":true,"decimalOdds":7.0},{"type":"X","state":"ACTIVE","displayed":true,"decimalOdds":1.2}],"channel":"INTERNET"}],"state":"OPEN","displayed":true,"type":"SOCCER:FT:AXB","subtype":"M"}]},"gatedMarkets":[],"bookmakerPrices":{"bookies":[{"bookie":"Bet365","marketPrices":{"market":[{"channel":[{"selection":[{"type":"XB","state":"ACTIVE","priceType":"LIVE_PRICE","displayed":true,"decimalOdds":1.083},{"type":"AB","state":"ACTIVE","priceType":"LIVE_PRICE","displayed":true,"decimalOdds":4.333}],"channel":"INTERNET"}],"state":"OPEN","type":"SOCCER:FT:DBLC","subtype":"M","line":""},{"channel":[{"selection":[{"type":"A","state":"ACTIVE","priceType":"LIVE_PRICE","displayed":true,"decimalOdds":7.0},{"type":"X","state":"ACTIVE","priceType":"LIVE_PRICE","displayed":true,"decimalOdds":1.2}],"channel":"INTERNET"}],"state":"OPEN","type":"SOCCER:FT:AXB","subtype":"M","line":""},{"channel":[{"selection":[{"type":"AH","state":"ACTIVE","name":"Biashara United -0.25","priceType":"LIVE_PRICE","displayed":true,"decimalOdds":4.3},{"type":"BH","state":"ACTIVE","name":"Ruvu Shooting -0.25","priceType":"LIVE_PRICE","displayed":true,"decimalOdds":1.19}],"channel":"INTERNET"}],"state":"OPEN","type":"SOCCER:FT:AHCP","subtype":"S0-0#-0.25","line":"-0.25"},{"channel":[{"selection":[{"type":"AH","state":"ACTIVE","name":"Biashara United 0.25","priceType":"LIVE_PRICE","displayed":true,"decimalOdds":1.13},{"type":"BH","state":"ACTIVE","name":"Ruvu Shooting +0.25","priceType":"LIVE_PRICE","displayed":true,"decimalOdds":5.4}],"channel":"INTERNET"}],"state":"OPEN","type":"SOCCER:FT:AHCP","subtype":"S0-0#0.25","line":"0.25"},{"channel":[{"selection":[{"type":"AH","state":"ACTIVE","name":"Biashara United +1","priceType":"LIVE_PRICE","displayed":true,"decimalOdds":1.062},{"type":"DH","state":"ACTIVE","name":"Draw -1","priceType":"LIVE_PRICE","displayed":true,"decimalOdds":10.0},{"type":"BH","state":"ACTIVE","name":"Ruvu Shooting -1","priceType":"LIVE_PRICE","displayed":true,"decimalOdds":81.0}],"channel":"INTERNET"}],"state":"OPEN","type":"SOCCER:FT:3HCP","subtype":"M#1","line":"1"},{"channel":[{"selection":[{"type":"AH","state":"ACTIVE","name":"Biashara United -1","priceType":"LIVE_PRICE","displayed":true,"decimalOdds":67.0},{"type":"DH","state":"ACTIVE","name":"Draw +1","priceType":"LIVE_PRICE","displayed":true,"decimalOdds":7.5},{"type":"BH","state":"ACTIVE","name":"Ruvu Shooting +1","priceType":"LIVE_PRICE","displayed":true,"decimalOdds":1.083}],"channel":"INTERNET"}],"state":"OPEN","type":"SOCCER:FT:3HCP","subtype":"M#-1","line":"-1"},{"channel":[{"selection":[{"type":"Over","state":"ACTIVE","priceType":"LIVE_PRICE","displayed":true,"decimalOdds":4.15},{"type":"Under","state":"ACTIVE","priceType":"LIVE_PRICE","displayed":true,"decimalOdds":1.22}],"channel":"INTERNET"}],"state":"OPEN","type":"SOCCER:FT:ASOU","subtype":"M#0.5","line":"0.5"},{"channel":[{"selection":[{"type":"Over","state":"ACTIVE","priceType":"LIVE_PRICE","displayed":true,"decimalOdds":6.4},{"type":"Under","state":"ACTIVE","priceType":"LIVE_PRICE","displayed":true,"decimalOdds":1.105}],"channel":"INTERNET"}],"state":"OPEN","type":"SOCCER:FT:ASOU","subtype":"M#0.75","line":"0.75"}]},"inplay":true,"eventId":5604129}],"eventId":5604129},"suspendedInChannels":[],"undisplayedInChannels":[],"gatedInChannels":[],"settings":[],"pitchers":[],"state":"ACTIVE","offeredInplay":true,"inplay":true,"displayed":true,"extId":"5604129"},"credential":{"username":"lsportsbetsyncuser","password":"dkd9hdg6283hbfdshdasidy23123"},"systemcode":"LSPORTS","partitioned":false}