{"eventTradingState":{"header":{"latencyTiming":{"activityTimes":[{"activity":"messageReceivedFromLsports","epoch":1593875467643},{"activity":"messageSentFromProxy","epoch":1593875467673},{"activity":"messageReceivedFromProxy","epoch":1593875467709},{"activity":"messageHandleInExecutor","epoch":1593875467709},{"activity":"sendingToBetsync","epoch":1593875467709}],"eventId":5614734,"originatingReqId":"9f0efed8-8242-4174-a507-e3f2859460dc","originatingProvider":"LSPORTS"}},"prices":{"market":[{"channel":[{"selection":[{"type":"Over","state":"ACTIVE","displayed":true,"decimalOdds":1.8},{"type":"Under","state":"ACTIVE","displayed":true,"decimalOdds":1.87}],"channel":"INTERNET"}],"state":"OPEN","displayed":true,"type":"BASKETBALL:FTOT:OU","subtype":"M#122.5"},{"channel":[{"selection":[{"type":"Under","state":"SUSPENDED","displayed":false},{"type":"Over","state":"SUSPENDED","displayed":false}],"channel":"INTERNET"}],"state":"SUSPENDED","displayed":false,"type":"BASKETBALL:FTOT:OU","subtype":"M#123.5"}]},"gatedMarkets":[],"suspendedInChannels":[],"undisplayedInChannels":[],"gatedInChannels":[],"settings":[],"pitchers":[],"state":"ACTIVE","offeredInplay":true,"inplay":true,"displayed":true,"extId":"5614734"},"credential":{"username":"lsportsbetsyncuser","password":"dkd9hdg6283hbfdshdasidy23123"},"systemcode":"LSPORTS","partitioned":false}