{"eventTradingState":{"header":{"latencyTiming":{"activityTimes":[{"activity":"messageReceivedFromLsports","epoch":1594027655702},{"activity":"messageSentFromProxy","epoch":1594027655706},{"activity":"messageReceivedFromProxy","epoch":1594027655710},{"activity":"messageHandleInExecutor","epoch":1594027655715},{"activity":"sendingToBetsync","epoch":1594027655715}],"eventId":5624809,"originatingReqId":"629a4762-21a1-4957-9f48-cef2a59f5766","originatingProvider":"LSPORTS"}},"prices":{"market":[]},"gatedMarkets":[],"suspendedInChannels":[],"undisplayedInChannels":[],"gatedInChannels":[],"settings":[],"pitchers":[],"state":"ACTIVE","offeredInplay":true,"inplay":true,"displayed":true,"extId":"5624809"},"credential":{"username":"lsportsbetsyncuser","password":"dkd9hdg6283hbfdshdasidy23123"},"systemcode":"LSPORTS","partitioned":false}