{"eventTradingState":{"header":{"latencyTiming":{"activityTimes":[{"activity":"messageReceivedFromLsports","epoch":1594025852295},{"activity":"messageSentFromProxy","epoch":1594025852304},{"activity":"messageReceivedFromProxy","epoch":1594025852306},{"activity":"messageHandleInExecutor","epoch":1594025852307},{"activity":"sendingToBetsync","epoch":1594025852307}],"eventId":5624809,"originatingReqId":"47a8a0e6-a15a-4970-96cc-1f2dba5a73a4","originatingProvider":"LSPORTS"}},"prices":{"market":[]},"gatedMarkets":[],"suspendedInChannels":[],"undisplayedInChannels":[],"gatedInChannels":[],"settings":[],"pitchers":[],"state":"ACTIVE","offeredInplay":true,"inplay":true,"displayed":true,"extId":"5624809"},"credential":{"username":"lsportsbetsyncuser","password":"dkd9hdg6283hbfdshdasidy23123"},"systemcode":"LSPORTS","partitioned":false}