{"eventTradingState":{"header":{"latencyTiming":{"activityTimes":[{"activity":"messageReceivedFromLsports","epoch":1594024514467},{"activity":"messageSentFromProxy","epoch":1594024514469},{"activity":"messageReceivedFromProxy","epoch":1594024514474},{"activity":"messageHandleInExecutor","epoch":1594024514480},{"activity":"sendingToBetsync","epoch":1594024514481}],"eventId":5624809,"originatingReqId":"34ce6b73-521c-4027-846e-63cf47a71036","originatingProvider":"LSPORTS"}},"prices":{"market":[]},"gatedMarkets":[],"suspendedInChannels":[],"undisplayedInChannels":[],"gatedInChannels":[],"settings":[],"pitchers":[],"state":"ACTIVE","offeredInplay":true,"inplay":true,"displayed":true,"extId":"5624809"},"credential":{"username":"lsportsbetsyncuser","password":"dkd9hdg6283hbfdshdasidy23123"},"systemcode":"LSPORTS","partitioned":false}