{"eventTradingState":{"header":{"latencyTiming":{"activityTimes":[{"activity":"messageReceivedFromLsports","epoch":1593956256222},{"activity":"messageSentFromProxy","epoch":1593956256235},{"activity":"messageReceivedFromProxy","epoch":1593956256238},{"activity":"messageHandleInExecutor","epoch":1593956256238},{"activity":"sendingToBetsync","epoch":1593956256239}],"eventId":5621067,"originatingReqId":"9fe6610e-634a-414a-95fd-61e079b389d7","originatingProvider":"LSPORTS"}},"prices":{"market":[{"channel":[{"selection":[{"type":"B","state":"SUSPENDED","displayed":false},{"type":"A","state":"SUSPENDED","displayed":false}],"channel":"INTERNET"}],"state":"SUSPENDED","displayed":false,"type":"TENNIS:G:ML","subtype":"S2.8"},{"channel":[{"selection":[{"type":"B","state":"SUSPENDED","displayed":false},{"type":"A","state":"SUSPENDED","displayed":false}],"channel":"INTERNET"}],"state":"SUSPENDED","displayed":false,"type":"TENNIS:G:ML","subtype":"S2.9"},{"channel":[{"selection":[{"type":"0-2","state":"SUSPENDED","displayed":false},{"type":"2-1","state":"SUSPENDED","displayed":false},{"type":"2-0","state":"SUSPENDED","displayed":false},{"type":"1-2","state":"SUSPENDED","displayed":false}],"channel":"INTERNET"}],"state":"SUSPENDED","displayed":false,"type":"TENNIS:FT:CS"},{"channel":[{"selection":[{"type":"A","state":"SUSPENDED","displayed":false},{"type":"B","state":"SUSPENDED","displayed":false}],"channel":"INTERNET"}],"state":"SUSPENDED","displayed":false,"type":"TENNIS:G:PW","subtype":"S2.9.1"},{"channel":[{"selection":[{"type":"B","state":"SUSPENDED","displayed":false},{"type":"A","state":"SUSPENDED","displayed":false}],"channel":"INTERNET"}],"state":"SUSPENDED","displayed":false,"type":"TENNIS:G:PW","subtype":"S2.8.12"},{"channel":[{"selection":[{"type":"B","state":"SUSPENDED","displayed":false},{"type":"A","state":"SUSPENDED","displayed":false}],"channel":"INTERNET"}],"state":"SUSPENDED","displayed":false,"type":"TENNIS:G:PW","subtype":"S2.8.11"},{"channel":[{"selection":[{"type":"A","state":"SUSPENDED","displayed":false},{"type":"B","state":"SUSPENDED","displayed":false}],"channel":"INTERNET"}],"state":"SUSPENDED","displayed":false,"type":"TENNIS:G:PW","subtype":"S2.8.13"}]},"gatedMarkets":[],"suspendedInChannels":[],"undisplayedInChannels":[],"gatedInChannels":[],"settings":[],"pitchers":[],"state":"ACTIVE","offeredInplay":true,"inplay":true,"displayed":true,"extId":"5621067"},"credential":{"username":"lsportsbetsyncuser","password":"dkd9hdg6283hbfdshdasidy23123"},"systemcode":"LSPORTS","partitioned":false}