{"eventTradingState":{"header":{"latencyTiming":{"activityTimes":[{"activity":"messageReceivedFromLsports","epoch":1593972772787},{"activity":"messageSentFromProxy","epoch":1593972772790},{"activity":"messageReceivedFromProxy","epoch":1593972772794},{"activity":"messageHandleInExecutor","epoch":1593972772794},{"activity":"sendingToBetsync","epoch":1593972772794}],"eventId":5620953,"originatingReqId":"58238e00-90ea-4edd-a7da-19338aaac034","originatingProvider":"LSPORTS"}},"prices":{"market":[]},"gatedMarkets":[],"suspendedInChannels":[],"undisplayedInChannels":[],"gatedInChannels":[],"settings":[],"pitchers":[],"state":"ACTIVE","offeredInplay":true,"inplay":true,"displayed":true,"extId":"5620953"},"credential":{"username":"lsportsbetsyncuser","password":"dkd9hdg6283hbfdshdasidy23123"},"systemcode":"LSPORTS","partitioned":false}