{"eventTradingState":{"header":{"latencyTiming":{"activityTimes":[{"activity":"messageReceivedFromLsports","epoch":1593975978932},{"activity":"messageSentFromProxy","epoch":1593975978990},{"activity":"messageReceivedFromProxy","epoch":1593975978997},{"activity":"messageHandleInExecutor","epoch":1593975978997},{"activity":"sendingToBetsync","epoch":1593975978998}],"eventId":5620953,"originatingReqId":"439a57a8-faad-4493-9ada-65738a3927ab","originatingProvider":"LSPORTS"}},"prices":{"market":[{"channel":[{"selection":[{"type":"Over","state":"ACTIVE","displayed":true,"decimalOdds":1.87},{"type":"Under","state":"ACTIVE","displayed":true,"decimalOdds":1.8}],"channel":"INTERNET"}],"state":"OPEN","displayed":true,"type":"BASKETBALL:FTOT:OU","subtype":"M#156.5"}]},"gatedMarkets":[],"suspendedInChannels":[],"undisplayedInChannels":[],"gatedInChannels":[],"settings":[],"pitchers":[],"state":"ACTIVE","offeredInplay":true,"inplay":true,"displayed":true,"extId":"5620953"},"credential":{"username":"lsportsbetsyncuser","password":"dkd9hdg6283hbfdshdasidy23123"},"systemcode":"LSPORTS","partitioned":false}