{"eventTradingState":{"header":{"latencyTiming":{"activityTimes":[{"activity":"messageReceivedFromLsports","epoch":1593978651693},{"activity":"messageSentFromProxy","epoch":1593978651693},{"activity":"messageReceivedFromProxy","epoch":1593978651696},{"activity":"messageHandleInExecutor","epoch":1593978651696},{"activity":"sendingToBetsync","epoch":1593978651696}],"eventId":5620953,"originatingReqId":"f286293f-750b-4105-813a-f8df8a5a3eda","originatingProvider":"LSPORTS"}},"gatedMarkets":[],"suspendedInChannels":[],"undisplayedInChannels":[],"gatedInChannels":[],"settings":[],"pitchers":[],"state":"SUSPENDED","inplay":false,"displayed":false,"extId":"5620953"},"credential":{"username":"lsportsbetsyncuser","password":"dkd9hdg6283hbfdshdasidy23123"},"systemcode":"LSPORTS","partitioned":false}