{"eventTradingState":{"header":{"latencyTiming":{"activityTimes":[{"activity":"messageReceivedFromLsports","epoch":1594461037440},{"activity":"messageSentFromProxy","epoch":1594461037440},{"activity":"messageReceivedFromProxy","epoch":1594461037442},{"activity":"messageHandleInExecutor","epoch":1594461037443},{"activity":"sendingToBetsync","epoch":1594461037443}],"eventId":5469904,"originatingReqId":"ac01d9d4-e78f-4695-a565-4b48a8db72af","originatingProvider":"LSPORTS"}},"gatedMarkets":[],"suspendedInChannels":[],"undisplayedInChannels":[],"gatedInChannels":[],"settings":[],"pitchers":[],"state":"SUSPENDED","inplay":false,"displayed":false,"extId":"5469904"},"credential":{"username":"lsportsbetsyncuser","password":"dkd9hdg6283hbfdshdasidy23123"},"systemcode":"LSPORTS","partitioned":false}