{"eventTradingState":{"header":{"latencyTiming":{"activityTimes":[{"activity":"messageReceivedFromLsports","epoch":1594381144682},{"activity":"messageSentFromProxy","epoch":1594381144733},{"activity":"messageReceivedFromProxy","epoch":1594381144735},{"activity":"messageHandleInExecutor","epoch":1594381144735},{"activity":"sendingToBetsync","epoch":1594381144736}],"eventId":5469904,"originatingReqId":"f21580f0-f55a-485c-b0f0-8b9617b60565","originatingProvider":"LSPORTS"}},"prices":{"market":[{"channel":[{"selection":[{"type":"Over","state":"SUSPENDED","displayed":false},{"type":"Under","state":"SUSPENDED","displayed":false}],"channel":"INTERNET"}],"state":"SUSPENDED","displayed":false,"type":"CRICKET:P:B:OU","subtype":"P1#330.5"},{"channel":[{"selection":[{"type":"Under","state":"SUSPENDED","displayed":false},{"type":"Over","state":"SUSPENDED","displayed":false}],"channel":"INTERNET"}],"state":"SUSPENDED","displayed":false,"type":"CRICKET:P:B:OU","subtype":"P1#280.5"},{"channel":[{"selection":[{"type":"Under","state":"SUSPENDED","displayed":false},{"type":"Over","state":"SUSPENDED","displayed":false}],"channel":"INTERNET"}],"state":"SUSPENDED","displayed":false,"type":"CRICKET:P:B:OU","subtype":"P1#344.5"},{"channel":[{"selection":[{"type":"Over","state":"SUSPENDED","displayed":false},{"type":"Under","state":"SUSPENDED","displayed":false}],"channel":"INTERNET"}],"state":"SUSPENDED","displayed":false,"type":"CRICKET:P:B:OU","subtype":"P1#380.5"},{"channel":[{"selection":[{"type":"Under","state":"SUSPENDED","displayed":false},{"type":"Over","state":"SUSPENDED","displayed":false}],"channel":"INTERNET"}],"state":"SUSPENDED","displayed":false,"type":"CRICKET:P:B:OU","subtype":"P1#244.5"},{"channel":[{"selection":[{"type":"Under","state":"SUSPENDED","displayed":false},{"type":"Over","state":"SUSPENDED","displayed":false}],"channel":"INTERNET"}],"state":"SUSPENDED","displayed":false,"type":"CRICKET:P:B:OU","subtype":"P1#294.5"},{"channel":[{"selection":[{"type":"Caught","state":"SUSPENDED","displayed":false},{"type":"Stumped","state":"SUSPENDED","displayed":false},{"type":"Lbw","state":"SUSPENDED","displayed":false},{"type":"Others","state":"SUSPENDED","displayed":false},{"type":"Run Out","state":"SUSPENDED","displayed":false},{"type":"Bowled","state":"SUSPENDED","displayed":false}],"channel":"INTERNET"}],"state":"SUSPENDED","displayed":false,"type":"CRICKET:P:MND6","subtype":"M"},{"channel":[{"selection":[{"type":"Yes","state":"SUSPENDED","displayed":false},{"type":"No","state":"SUSPENDED","displayed":false}],"channel":"INTERNET"}],"state":"SUSPENDED","displayed":false,"type":"CRICKET:P:BOW","subtype":"O43"},{"channel":[{"selection":[{"type":"Not Caught","state":"SUSPENDED","displayed":false},{"type":"Caught","state":"SUSPENDED","displayed":false}],"channel":"INTERNET"}],"state":"SUSPENDED","displayed":false,"type":"CRICKET:P:ND","subtype":"M{0}"},{"channel":[{"selection":[{"type":"B","state":"SUSPENDED","displayed":false},{"type":"X","state":"SUSPENDED","displayed":false},{"type":"A","state":"SUSPENDED","displayed":false}],"channel":"INTERNET"}],"state":"SUSPENDED","displayed":false,"type":"CRICKET:P:AXB","subtype":"I1"}]},"gatedMarkets":[],"suspendedInChannels":[],"undisplayedInChannels":[],"gatedInChannels":[],"settings":[],"pitchers":[],"state":"ACTIVE","offeredInplay":true,"inplay":true,"displayed":true,"extId":"5469904"},"credential":{"username":"lsportsbetsyncuser","password":"dkd9hdg6283hbfdshdasidy23123"},"systemcode":"LSPORTS","partitioned":false}