{"eventTradingState":{"header":{"latencyTiming":{"activityTimes":[{"activity":"messageReceivedFromLsports","epoch":1594303985704},{"activity":"messageSentFromProxy","epoch":1594303985726},{"activity":"messageReceivedFromProxy","epoch":1594303985728},{"activity":"messageHandleInExecutor","epoch":1594303985728},{"activity":"sendingToBetsync","epoch":1594303985728}],"eventId":5469904,"originatingReqId":"a44bd158-4921-4440-a09f-2fc8e65b3d2c","originatingProvider":"LSPORTS"}},"prices":{"market":[{"channel":[{"selection":[{"type":"X","state":"ACTIVE","displayed":true,"decimalOdds":12.0}],"channel":"INTERNET"}],"state":"OPEN","displayed":true,"type":"CRICKET:FT:AXB","subtype":"M"}]},"gatedMarkets":[],"suspendedInChannels":[],"undisplayedInChannels":[],"gatedInChannels":[],"settings":[],"pitchers":[],"state":"SUSPENDED","inplay":false,"displayed":false,"extId":"5469904"},"credential":{"username":"lsportsbetsyncuser","password":"dkd9hdg6283hbfdshdasidy23123"},"systemcode":"LSPORTS","partitioned":false}