{"eventTradingState":{"header":{"latencyTiming":{"activityTimes":[{"activity":"messageReceivedFromLsports","epoch":1593960233251},{"activity":"messageSentFromProxy","epoch":1593960233262},{"activity":"messageReceivedFromProxy","epoch":1593960233266},{"activity":"messageHandleInExecutor","epoch":1593960233266},{"activity":"sendingToBetsync","epoch":1593960233267}],"eventId":5620807,"originatingReqId":"d4d8f11d-f460-44d6-9c6c-fa6b22d0741c","originatingProvider":"LSPORTS"}},"prices":{"market":[{"channel":[{"selection":[{"type":"B","state":"ACTIVE","displayed":true,"decimalOdds":1.444},{"type":"A","state":"ACTIVE","displayed":true,"decimalOdds":2.625}],"channel":"INTERNET"}],"state":"OPEN","displayed":true,"type":"TENNIS:G:ML","subtype":"S2.9"},{"channel":[{"selection":[{"type":"0-2","state":"ACTIVE","displayed":true,"decimalOdds":1.533},{"type":"1-2","state":"ACTIVE","displayed":true,"decimalOdds":3.6},{"type":"2-1","state":"ACTIVE","displayed":true,"decimalOdds":5.5}],"channel":"INTERNET"}],"state":"OPEN","displayed":true,"type":"TENNIS:FT:CS"},{"channel":[{"selection":[{"type":"BH","state":"ACTIVE","displayed":true,"decimalOdds":1.444},{"type":"AH","state":"ACTIVE","displayed":true,"decimalOdds":2.625}],"channel":"INTERNET"}],"state":"OPEN","displayed":true,"type":"TENNIS:P:RX","subtype":"S2#5.0"},{"channel":[{"selection":[{"type":"A","state":"ACTIVE","displayed":true,"decimalOdds":5.5},{"type":"B","state":"ACTIVE","displayed":true,"decimalOdds":1.125}],"channel":"INTERNET"}],"state":"OPEN","displayed":true,"type":"TENNIS:FT:ML","subtype":"M"},{"channel":[{"selection":[{"type":"B","state":"ACTIVE","displayed":true,"decimalOdds":1.533},{"type":"A","state":"ACTIVE","displayed":true,"decimalOdds":2.375}],"channel":"INTERNET"}],"state":"OPEN","displayed":true,"type":"TENNIS:P:ML","subtype":"S2"}]},"gatedMarkets":[],"suspendedInChannels":[],"undisplayedInChannels":[],"gatedInChannels":[],"settings":[],"pitchers":[],"state":"ACTIVE","offeredInplay":true,"inplay":true,"displayed":true,"extId":"5620807"},"credential":{"username":"lsportsbetsyncuser","password":"dkd9hdg6283hbfdshdasidy23123"},"systemcode":"LSPORTS","partitioned":false}