{"TennisMatchIncident":{"subClass":"TennisMatchIncident","undo":false,"elapsedTimeSecs":0,"eventId":0,"incidentId":"97476f27-615a-49e3-968b-6d18fe1357fd","teamId":"B","sourceSystem":"LSPORTS","externalEventId":"5620907","incidentFeedTimeStamp":0,"matchStateFromFeed":{"subClass":"TennisMatchStateFromFeed","setsA":0,"setsB":0,"gamesA":2,"gamesB":2,"pointsA":3,"pointsB":4,"tiebreak":false,"teamServingNow":"A","playerServingNow":"A1"},"incidentSubType":"POINT_WON","serverSideAtStartOfMatch":"A","serverPlayerAtStartOfMatch":0,"serverPlayerAtStartOfCurrentGame":0,"pointWinner":"B"}}